IntellijIdeaShiyongJiaochengV10/README.md
IntellijIdeaShiyongJiaochengV10/__init__.py
IntellijIdeaShiyongJiaochengV10/__main__.py
IntellijIdeaShiyongJiaochengV10/file.epub
IntellijIdeaShiyongJiaochengV10/index.html
IntellijIdeaShiyongJiaochengV10/css/__init__.py
IntellijIdeaShiyongJiaochengV10/css/annotations.css
IntellijIdeaShiyongJiaochengV10/css/main.css
IntellijIdeaShiyongJiaochengV10/css/normalize.css
IntellijIdeaShiyongJiaochengV10/css/popup.css
IntellijIdeaShiyongJiaochengV10/font/__init__.py
IntellijIdeaShiyongJiaochengV10/font/fontello.eot
IntellijIdeaShiyongJiaochengV10/font/fontello.svg
IntellijIdeaShiyongJiaochengV10/font/fontello.ttf
IntellijIdeaShiyongJiaochengV10/font/fontello.woff
IntellijIdeaShiyongJiaochengV10/img/__init__.py
IntellijIdeaShiyongJiaochengV10/img/annotator-glyph-sprite.png
IntellijIdeaShiyongJiaochengV10/img/annotator-icon-sprite.png
IntellijIdeaShiyongJiaochengV10/img/apple-touch-icon.png
IntellijIdeaShiyongJiaochengV10/img/cancelfullscreen.png
IntellijIdeaShiyongJiaochengV10/img/close.png
IntellijIdeaShiyongJiaochengV10/img/fullscreen.png
IntellijIdeaShiyongJiaochengV10/img/loader.gif
IntellijIdeaShiyongJiaochengV10/img/menu-icon.png
IntellijIdeaShiyongJiaochengV10/img/save.png
IntellijIdeaShiyongJiaochengV10/img/saved.png
IntellijIdeaShiyongJiaochengV10/img/settings-s.png
IntellijIdeaShiyongJiaochengV10/img/settings.png
IntellijIdeaShiyongJiaochengV10/img/star.png
IntellijIdeaShiyongJiaochengV10/js/__init__.py
IntellijIdeaShiyongJiaochengV10/js/epub.js
IntellijIdeaShiyongJiaochengV10/js/epub.min.js
IntellijIdeaShiyongJiaochengV10/js/epub.min.map
IntellijIdeaShiyongJiaochengV10/js/hooks.min.js
IntellijIdeaShiyongJiaochengV10/js/hooks.min.map
IntellijIdeaShiyongJiaochengV10/js/reader.js
IntellijIdeaShiyongJiaochengV10/js/reader.js.map
IntellijIdeaShiyongJiaochengV10/js/reader.min.js
IntellijIdeaShiyongJiaochengV10/js/reader.min.map
IntellijIdeaShiyongJiaochengV10/js/hooks/__init__.py
intellij_idea_shiyong_jiaocheng_v1_0-2024.3.2.0.dist-info/METADATA
intellij_idea_shiyong_jiaocheng_v1_0-2024.3.2.0.dist-info/WHEEL
intellij_idea_shiyong_jiaocheng_v1_0-2024.3.2.0.dist-info/entry_points.txt
intellij_idea_shiyong_jiaocheng_v1_0-2024.3.2.0.dist-info/top_level.txt
intellij_idea_shiyong_jiaocheng_v1_0-2024.3.2.0.dist-info/RECORD
